setup.py
ez_setup/README.txt
ez_setup/__init__.py
simple_json/__init__.py
simple_json.egg-info/PKG-INFO
simple_json.egg-info/SOURCES.txt
simple_json.egg-info/requires.txt
simple_json.egg-info/top_level.txt
simple_json.egg-info/zip-safe
