Metadata-Version: 1.0
Name: simple-json
Version: 1.1
Summary: Compatibility shim for simplejson
Home-page: http://undefined.org/python/#simple_json
Author: Bob Ippolito
Author-email: bob@redivi.com
License: MIT License
Platform: any
Classifier: Intended Audience :: Developers
Classifier: License :: OSI Approved :: MIT License
Classifier: Programming Language :: Python
Classifier: Topic :: Software Development :: Libraries :: Python Modules
